stegbox.py
stegbox-1.0.dist-info/LICENSE
stegbox-1.0.dist-info/METADATA
stegbox-1.0.dist-info/WHEEL
stegbox-1.0.dist-info/entry_points.txt
stegbox-1.0.dist-info/top_level.txt
stegbox-1.0.dist-info/RECORD
