Metadata-Version: 2.1
Name: stegbox
Version: 1.0
Summary: A CLI tool for embedding and extracting files in images using steganography
Home-page: https://github.com/hasib9797/stegbox
Author: Hasib
Author-email: hasib69780@gmail.com
Classifier: Programming Language :: Python :: 3
Classifier: License :: OSI Approved :: MIT License
Classifier: Operating System :: OS Independent
Requires-Python: >=3.6
License-File: LICENSE
Requires-Dist: Pillow
Requires-Dist: bitarray
